tiktok_get_info/__init__.py
tiktok_get_info/info.py
tiktok_get_info-10.10.dist-info/entry_points.txt
tiktok_get_info-10.10.dist-info/WHEEL
tiktok_get_info-10.10.dist-info/METADATA
tiktok_get_info-10.10.dist-info/RECORD
