Metadata-Version: 2.3
Name: tiktok_get_info
Version: 10.10
Summary: TikTok Info: Module for retrieving and processing information from TikTok.
Author-email: bilalsbxp <bilalsaputra641@gmail.com>
Project-URL: Home, https://pypi.org/project/tiktok_get_info
